period_iterator/__init__.py
period_iterator/period_cursor.py
period_iterator/period_iterator.py
period_iterator/period_timezone.py
period_iterator/tests/__init__.py
period_iterator/tests/test_period_cursor.py
period_iterator/tests/test_period_iterator.py
period_iterator/tests/test_period_timezone.py
period_iterator-1.3.0.dist-info/LICENSE
period_iterator-1.3.0.dist-info/METADATA
period_iterator-1.3.0.dist-info/WHEEL
period_iterator-1.3.0.dist-info/top_level.txt
period_iterator-1.3.0.dist-info/RECORD
