Metadata-Version: 2.1
Name: period-iterator
Version: 1.3.0
Summary: Period Iterator
Home-page: https://github.com/chonla/period-iterator
Author: Chonlasith Jucksriporn
Author-email: chonlasith@gmail.com
License: MIT
Keywords: period,iterator
Classifier: Development Status :: 5 - Production/Stable
Classifier: Intended Audience :: Developers
Classifier: Topic :: Software Development :: Build Tools
Classifier: License :: OSI Approved :: MIT License
Classifier: Programming Language :: Python :: 3.7
Classifier: Programming Language :: Python :: 3.8
Classifier: Programming Language :: Python :: 3.9
Classifier: Programming Language :: Python :: 3.10
Classifier: Programming Language :: Python :: 3.11
Requires-Python: >=3.7, <4
License-File: LICENSE
Requires-Dist: python-dateutil
Requires-Dist: pytz
